timekan/__init__.py
timekan/layers/__init__.py
timekan/layers/chebyshev.py
timekan/layers/fourier.py
timekan/layers/relu.py
timekan/layers/spline.py
timekan/models/__init__.py
timekan/models/tkan_gru.py
timekan/models/tkan_lstm.py
timekan/utils/__init__.py
timekan/utils/datasets.py
timekan-0.1.3.dist-info/METADATA
timekan-0.1.3.dist-info/WHEEL
timekan-0.1.3.dist-info/top_level.txt
timekan-0.1.3.dist-info/RECORD
