Metadata-Version: 2.2
Name: timekan
Version: 0.1.3
Summary: Python library designed to integrate Kolmogorov Arnold Networks with recurrent mechanisms.
Home-page: https://github.com/samermakni/timekan
Author: Samer Makni
Author-email: samermakni@outlook.com
Classifier: Programming Language :: Python :: 3
Classifier: License :: OSI Approved :: MIT License
Classifier: Operating System :: OS Independent
Requires-Python: >=3.9
Requires-Dist: torch>=2.4.0
Requires-Dist: numpy>=1.20.0
Requires-Dist: cuda_selector>=0.1.0
Dynamic: author
Dynamic: author-email
Dynamic: classifier
Dynamic: description
Dynamic: description-content-type
Dynamic: home-page
Dynamic: requires-dist
Dynamic: requires-python
Dynamic: summary
